__init__.py
snippets_yw/__init__.py
snippets_yw-0.0.1.dist-info/LICENSE
snippets_yw-0.0.1.dist-info/METADATA
snippets_yw-0.0.1.dist-info/WHEEL
snippets_yw-0.0.1.dist-info/top_level.txt
snippets_yw-0.0.1.dist-info/RECORD
