Metadata-Version: 2.1
Name: snippets_yw
Version: 0.0.1
Summary: Snippets
Author-email: "y@wildfluss.com" <y@wildfluss.com>
Project-URL: Homepage, https://github.com/wildfluss/snippets_yw
Project-URL: Bug Tracker, https://github.com/wildfluss/snippets_yw/issues
Classifier: Programming Language :: Python :: 3
Classifier: License :: OSI Approved :: MIT License
Classifier: Operating System :: OS Independent
Requires-Python: >=3.11
License-File: LICENSE
